{
  "voicevox_url": "http://localhost:50021",
  "speakers": {
    "ずんだもん": 3,
    "めたん": 2
  },
  "speed_scale": 1.14,
  "inter_line_silence": 0.3,
  "scene_end_padding": 0.5,
  "scenes": [
    {
      "id": 0,
      "title": "腸が脳を支配する？",
      "lines": [
        { "speaker": "めたん", "text": "ねえずんだもん、ちょっと聞いてもいいですの？" },
        { "speaker": "ずんだもん", "text": "もちろんなのだ。何でも聞いてほしいのだ。" },
        { "speaker": "めたん", "text": "お腹の調子が悪いと、なんだか気分まで落ち込みませんの？" },
        { "speaker": "ずんだもん", "text": "それ、実は気のせいじゃなかったのだ。" },
        { "speaker": "めたん", "text": "え、本当ですの？" },
        { "speaker": "ずんだもん", "text": "うん。科学的に証明されてる現象なのだ。" }
      ]
    },
    {
      "id": 1,
      "title": "腸は「第二の脳」と呼ばれている",
      "lines": [
        { "speaker": "ずんだもん", "text": "実はね、腸には「第二の脳」って呼ばれる神経系があるのだ。" },
        { "speaker": "めたん", "text": "第二の脳……？　腸に脳みたいなものがあるんですの？" },
        { "speaker": "ずんだもん", "text": "正式には「腸管神経系」って言うのだ。" },
        { "speaker": "ずんだもん", "text": "英語だとEnteric Nervous System、略してENSなのだ。" },
        { "speaker": "めたん", "text": "何だか難しそうですわね……。" },
        { "speaker": "ずんだもん", "text": "難しくないのだ。腸の壁の中に張り巡らされた神経のネットワークなのだ。" }
      ]
    },
    {
      "id": 2,
      "title": "2億〜6億個の神経細胞",
      "lines": [
        { "speaker": "ずんだもん", "text": "そしてこのENSには、2億から6億個もの神経細胞があるのだ。" },
        { "speaker": "めたん", "text": "億単位！？　それは想像以上ですわ。" },
        { "speaker": "ずんだもん", "text": "これ、実は脊髄の神経細胞よりも多いのだ。" },
        { "speaker": "めたん", "text": "脊髄より多い神経が腸にあるなんて驚きですわね。" },
        { "speaker": "ずんだもん", "text": "しかもこの神経細胞たち、脳からの指令がなくても動けるのだ。" },
        { "speaker": "めたん", "text": "え、脳の命令なしで？" },
        { "speaker": "ずんだもん", "text": "そう。腸の動きや消化液の分泌を独立して制御してるのだ。" }
      ]
    },
    {
      "id": 3,
      "title": "この動画でわかる3つのこと",
      "lines": [
        { "speaker": "めたん", "text": "それで「第二の脳」って呼ばれてるんですわね。" },
        { "speaker": "ずんだもん", "text": "そういうことなのだ。でも実はこの呼び方、ちょっと問題もあるのだ。" },
        { "speaker": "ずんだもん", "text": "それは後で詳しく話すとして、まず今日の構成を紹介するのだ。" },
        { "speaker": "ずんだもん", "text": "1つ目は、腸と脳がどうやって会話しているのか。" },
        { "speaker": "ずんだもん", "text": "2つ目は、腸内細菌がメンタルにどう影響するのか。" },
        { "speaker": "ずんだもん", "text": "3つ目は、パーキンソン病が腸から始まるかもしれない驚きの研究なのだ。" },
        { "speaker": "めたん", "text": "3つ目がもう気になりますわ！　早速始めましょう！" }
      ]
    },
    {
      "id": 4,
      "title": "腸脳軸の双方向コミュニケーション",
      "lines": [
        { "speaker": "ずんだもん", "text": "まず、腸と脳がどうやって会話してるか説明するのだ。" },
        { "speaker": "ずんだもん", "text": "専門用語で「腸脳軸」って呼ばれてるのだ。" },
        { "speaker": "めたん", "text": "チョウノウジクですの？　何だかかっこいい名前ですわね。" },
        { "speaker": "ずんだもん", "text": "英語だとgut-brain axisなのだ。" },
        { "speaker": "ずんだもん", "text": "簡単に言うと、腸と脳をつなぐ通信回線のことなのだ。" },
        { "speaker": "めたん", "text": "通信回線ですの。電話みたいなものですわね。" },
        { "speaker": "ずんだもん", "text": "いい例えなのだ。しかもこの電話、一方通行じゃないのだ。" },
        { "speaker": "ずんだもん", "text": "腸から脳にも、脳から腸にも情報が送られる双方向通信なのだ。" }
      ]
    },
    {
      "id": 5,
      "title": "迷走神経の80〜90%は腸→脳方向",
      "lines": [
        { "speaker": "ずんだもん", "text": "この通信回線の主役が「迷走神経」っていう神経なのだ。" },
        { "speaker": "めたん", "text": "迷走神経ですの。名前からして迷子になりそうですわ。" },
        { "speaker": "ずんだもん", "text": "名前の由来は確かに「迷うように走る」からなのだ。" },
        { "speaker": "ずんだもん", "text": "脳から腸まで複雑な経路で走ってるからそう呼ばれるのだ。" },
        { "speaker": "ずんだもん", "text": "でね、ここが重要なのだ。" },
        { "speaker": "ずんだもん", "text": "迷走神経の繊維の80〜90%は、腸から脳の方向なのだ。" },
        { "speaker": "めたん", "text": "80〜90%！？　ほとんど腸から脳ですの！？" }
      ]
    },
    {
      "id": 6,
      "title": "脳→腸 vs 腸→脳",
      "lines": [
        { "speaker": "ずんだもん", "text": "脳から腸へはたった10〜20%しかないのだ。" },
        { "speaker": "ずんだもん", "text": "つまり情報量で言えば、腸のほうが圧倒的におしゃべりなのだ。" },
        { "speaker": "めたん", "text": "脳が司令塔だと思ってたのに、腸が大量に情報を送ってるなんて意外ですわ。" },
        { "speaker": "ずんだもん", "text": "そうなのだ。腸は黙って消化してるだけじゃなくて……" },
        { "speaker": "ずんだもん", "text": "脳に向かって絶え間なく報告を送ってるのだ。" },
        { "speaker": "めたん", "text": "緊張するとお腹が痛くなるのも、この仕組みが関係してるんですの？" }
      ]
    },
    {
      "id": 7,
      "title": "「腹が立つ」は科学だった",
      "lines": [
        { "speaker": "ずんだもん", "text": "鋭いのだ。まさにその通りなのだ。" },
        { "speaker": "ずんだもん", "text": "「腹が立つ」「はらわたが煮えくり返る」って日本語があるよね。" },
        { "speaker": "めたん", "text": "ありますわね。お腹と感情を結びつける言い方ですわ。" },
        { "speaker": "ずんだもん", "text": "英語にも「gut feeling」っていう直感を表す言葉があるのだ。" },
        { "speaker": "ずんだもん", "text": "これ、ただの比喩じゃなくて科学的な裏付けがあったのだ。" },
        { "speaker": "めたん", "text": "昔の人は体で腸脳軸を感じ取ってたんですわね。" }
      ]
    },
    {
      "id": 8,
      "title": "腸から脳に送られる情報の種類",
      "lines": [
        { "speaker": "めたん", "text": "具体的にどんな情報が送られてるんですの？" },
        { "speaker": "ずんだもん", "text": "大きく分けて3つの種類があるのだ。" },
        { "speaker": "ずんだもん", "text": "まず栄養素の情報。「今こんな食べ物が来たよ」っていう報告なのだ。" },
        { "speaker": "ずんだもん", "text": "次に免疫の状態。「異物が侵入したよ」っていう警報なのだ。" },
        { "speaker": "ずんだもん", "text": "そして3つ目が、腸内細菌が作る化学物質の情報なのだ。" },
        { "speaker": "めたん", "text": "腸内細菌が化学物質を作るんですの？" }
      ]
    },
    {
      "id": 9,
      "title": "セロトニンの90%以上は腸で生成",
      "lines": [
        { "speaker": "ずんだもん", "text": "ここが今日一番の驚きポイントかもしれないのだ。" },
        { "speaker": "ずんだもん", "text": "「幸せホルモン」って呼ばれるセロトニン。" },
        { "speaker": "ずんだもん", "text": "聞いたことある人も多いと思うのだ。" },
        { "speaker": "めたん", "text": "セロトニンですわね。気分を良くしてくれるやつですわ。" },
        { "speaker": "ずんだもん", "text": "そのセロトニンの90%以上は、実は脳じゃなくて腸で作られてるのだ。" },
        { "speaker": "めたん", "text": "90%以上が腸で！？　嘘みたいですわ！" },
        { "speaker": "ずんだもん", "text": "本当の話なのだ。でもね、この事実には重大な注意点があるのだ。" },
        { "speaker": "ずんだもん", "text": "これは後で詳しく説明するから、覚えておいてほしいのだ。" },
        { "speaker": "めたん", "text": "じらしますわね……早く知りたいですわ！" }
      ]
    },
    {
      "id": 10,
      "title": "腸内細菌とメンタルヘルス",
      "lines": [
        { "speaker": "ずんだもん", "text": "じゃあ、腸内細菌がメンタルにどう影響するか話していくのだ。" },
        { "speaker": "めたん", "text": "腸内細菌って、お腹にいるいろんな種類の菌のことですわよね。" },
        { "speaker": "ずんだもん", "text": "そうなのだ。まず数字から紹介すると驚くと思うのだ。" }
      ]
    },
    {
      "id": 11,
      "title": "腸内細菌100兆個、重さ1〜2kg",
      "lines": [
        { "speaker": "ずんだもん", "text": "人間の腸の中には約1000種類、100兆個以上の細菌がいるのだ。" },
        { "speaker": "めたん", "text": "100兆個ですの！？" },
        { "speaker": "ずんだもん", "text": "しかも全部合わせると重さが1〜2キログラムもあるのだ。" },
        { "speaker": "めたん", "text": "1キロ以上も細菌が住んでるなんて、ちょっと衝撃ですわ。" },
        { "speaker": "ずんだもん", "text": "ちなみに人間の体の細胞は約37兆個なのだ。" },
        { "speaker": "ずんだもん", "text": "つまり数だけで言えば、自分の細胞より細菌のほうが多いのだ。" },
        { "speaker": "めたん", "text": "自分の体にいる細菌のほうが多いなんて不思議な気分ですわ。" },
        { "speaker": "ずんだもん", "text": "しかも面白いことに、腸内細菌の構成は人によって全然違うのだ。" },
        { "speaker": "ずんだもん", "text": "食生活や生活環境、さらには3歳までの環境で大体決まるのだ。" },
        { "speaker": "めたん", "text": "3歳までに決まるんですの？　それは意外ですわ。" }
      ]
    },
    {
      "id": 12,
      "title": "腸内細菌がメンタルに影響する3つの経路",
      "lines": [
        { "speaker": "ずんだもん", "text": "で、この腸内細菌たちがメンタルに影響する経路が3つあるのだ。" },
        { "speaker": "ずんだもん", "text": "1つ目は、さっき話したセロトニンなどの神経伝達物質の生成なのだ。" },
        { "speaker": "めたん", "text": "90%が腸で作られるっていうやつですわね。" },
        { "speaker": "ずんだもん", "text": "そう。腸内細菌はセロトニンだけじゃなくて……" },
        { "speaker": "ずんだもん", "text": "ドーパミンやGABAなどの神経伝達物質も作ってるのだ。" },
        { "speaker": "めたん", "text": "ドーパミンまで！？　やる気の物質じゃないですの。" },
        { "speaker": "ずんだもん", "text": "2つ目は「短鎖脂肪酸」っていう物質の生成なのだ。" },
        { "speaker": "めたん", "text": "タンサシボウサンですの？　聞いたことないですわ。" }
      ]
    },
    {
      "id": 13,
      "title": "短鎖脂肪酸の3つの働き",
      "lines": [
        { "speaker": "ずんだもん", "text": "食物繊維が腸内細菌によって分解されるとできる物質なのだ。" },
        { "speaker": "ずんだもん", "text": "代表的なのが「酪酸」っていうものなのだ。" },
        { "speaker": "ずんだもん", "text": "この短鎖脂肪酸には大きく3つの働きがあるのだ。" },
        { "speaker": "ずんだもん", "text": "1つ、ストレス応答を緩和する。" },
        { "speaker": "ずんだもん", "text": "2つ、体の炎症を抑える。" },
        { "speaker": "ずんだもん", "text": "3つ、脳の神経を保護するBDNFっていう物質を増やすのだ。" },
        { "speaker": "めたん", "text": "BDNFって何ですの？" },
        { "speaker": "ずんだもん", "text": "脳由来神経栄養因子って言って、脳の神経細胞を守る物質なのだ。" },
        { "speaker": "ずんだもん", "text": "つまり食物繊維を食べると、腸内細菌が脳を守る物質を作ってくれるのだ。" },
        { "speaker": "めたん", "text": "食物繊維がそんな大事な働きにつながるなんて知りませんでしたわ。" }
      ]
    },
    {
      "id": 14,
      "title": "免疫細胞の70%が腸に集中",
      "lines": [
        { "speaker": "ずんだもん", "text": "そして3つ目の経路が免疫系なのだ。" },
        { "speaker": "ずんだもん", "text": "これも驚くと思うけど、人間の免疫細胞の70%が腸に集中してるのだ。" },
        { "speaker": "めたん", "text": "70%も！？　腸って体の免疫の本部みたいですわね。" },
        { "speaker": "ずんだもん", "text": "まさにその通りなのだ。" },
        { "speaker": "ずんだもん", "text": "外から入ってくる病原菌やウイルスを最前線で迎え撃つのが腸なのだ。" },
        { "speaker": "ずんだもん", "text": "腸の免疫が乱れると、全身の炎症バランスも崩れて……" },
        { "speaker": "ずんだもん", "text": "それが脳にも悪影響を及ぼすことがわかってきてるのだ。" },
        { "speaker": "めたん", "text": "腸って消化だけじゃなくて、免疫も担ってるなんてすごいですわね。" }
      ]
    },
    {
      "id": 15,
      "title": "セロトニンの誤解に注意",
      "lines": [
        { "speaker": "ずんだもん", "text": "さて、ここでさっき予告した大事な注意点を話すのだ。" },
        { "speaker": "めたん", "text": "セロトニンの話ですわね。ずっと気になってましたわ。" },
        { "speaker": "ずんだもん", "text": "セロトニンの90%以上が腸で作られるのは事実なのだ。" },
        { "speaker": "ずんだもん", "text": "でもね、腸で作られたセロトニンは「血液脳関門」を通れないのだ。" },
        { "speaker": "めたん", "text": "血液脳関門ですの？" }
      ]
    },
    {
      "id": 16,
      "title": "腸のセロトニンは脳に直接届かない",
      "lines": [
        { "speaker": "ずんだもん", "text": "脳を有害物質から守るバリアのことなのだ。" },
        { "speaker": "ずんだもん", "text": "このバリアがあるから、腸のセロトニンは脳に直接は届かないのだ。" },
        { "speaker": "めたん", "text": "え！？　じゃあ腸でセロトニンをたくさん作っても意味ないんですの？" },
        { "speaker": "ずんだもん", "text": "意味がないわけじゃないのだ。間接的には影響するのだ。" },
        { "speaker": "ずんだもん", "text": "腸のセロトニンが迷走神経を刺激したり……" },
        { "speaker": "ずんだもん", "text": "ホルモンバランスに影響して、結果的に脳に作用するのだ。" },
        { "speaker": "めたん", "text": "直接じゃなくて、回り道をして影響するんですわね。" },
        { "speaker": "ずんだもん", "text": "でも「腸のセロトニンで直接ハッピーになる」は言い過ぎなのだ。" },
        { "speaker": "ずんだもん", "text": "ここを正しく理解するのが、腸活の第一歩なのだ。" },
        { "speaker": "めたん", "text": "科学って正確に理解するのが大切ですわね……。" },
        { "speaker": "ずんだもん", "text": "でもね、腸と脳の関係には、この先もっと驚く話があるのだ。" }
      ]
    },
    {
      "id": 17,
      "title": "腸から始まる病気？",
      "lines": [
        { "speaker": "ずんだもん", "text": "ここからがさらに衝撃的な話なのだ。" },
        { "speaker": "ずんだもん", "text": "パーキンソン病って知ってるかな？" },
        { "speaker": "めたん", "text": "手が震えたり、体の動きが鈍くなる病気ですわよね。" },
        { "speaker": "ずんだもん", "text": "そう。ずっと「脳の病気」だと考えられてきたのだ。" },
        { "speaker": "ずんだもん", "text": "脳内のドーパミンを作る神経細胞が壊れていく病気なのだ。" },
        { "speaker": "めたん", "text": "脳の神経が壊れるなんて怖い病気ですわね。" },
        { "speaker": "ずんだもん", "text": "でも最近の研究で、この常識が覆されようとしてるのだ。" }
      ]
    },
    {
      "id": 18,
      "title": "α-シヌクレインが腸→迷走神経→脳へ",
      "lines": [
        { "speaker": "めたん", "text": "脳の病気じゃないかもしれないってことですの？" },
        { "speaker": "ずんだもん", "text": "パーキンソン病の原因とされるタンパク質があるのだ。" },
        { "speaker": "ずんだもん", "text": "「α-シヌクレイン」っていう名前なのだ。" },
        { "speaker": "めたん", "text": "アルファシヌクレインですの。難しい名前ですわね。" },
        { "speaker": "ずんだもん", "text": "このタンパク質は、正常なら脳内で良い働きをするのだ。" },
        { "speaker": "ずんだもん", "text": "でも異常な形に変化すると、神経細胞を壊していくのだ。" },
        { "speaker": "ずんだもん", "text": "で、驚くべきことに、この異常なタンパク質が……" },
        { "speaker": "ずんだもん", "text": "腸で最初に作られて、迷走神経を通って脳に届く可能性が出てきたのだ。" },
        { "speaker": "めたん", "text": "腸から脳に病気が「のぼっていく」ですの！？" }
      ]
    },
    {
      "id": 19,
      "title": "迷走神経切断でパーキンソン病リスク半減",
      "lines": [
        { "speaker": "ずんだもん", "text": "これを裏付ける証拠がいくつもあるのだ。" },
        { "speaker": "ずんだもん", "text": "昔、胃潰瘍の治療で迷走神経を切断する手術があったのだ。" },
        { "speaker": "ずんだもん", "text": "この手術を受けた人のデータを調べたら……" },
        { "speaker": "ずんだもん", "text": "パーキンソン病の発症率が約半分に低下してたのだ。" },
        { "speaker": "めたん", "text": "半分ですの！？　それはかなりの差ですわね。" },
        { "speaker": "ずんだもん", "text": "もし腸と脳が関係ないなら、こんな差は出ないはずなのだ。" }
      ]
    },
    {
      "id": 20,
      "title": "発症の20年前から腸に兆候",
      "lines": [
        { "speaker": "ずんだもん", "text": "さらに注目すべきデータがあるのだ。" },
        { "speaker": "ずんだもん", "text": "パーキンソン病の患者さんは、発症の約20年も前から……" },
        { "speaker": "ずんだもん", "text": "便秘などの腸の症状が出ていることが多いのだ。" },
        { "speaker": "めたん", "text": "20年前から！？　腸がずっとサインを出してたんですわね……。" },
        { "speaker": "ずんだもん", "text": "もしこれが証明されたら、腸を調べることで早期発見できるかもしれないのだ。" },
        { "speaker": "めたん", "text": "脳の病気を腸で見つけるなんて、医学の常識が変わりますわね。" }
      ]
    },
    {
      "id": 21,
      "title": "うつ病マウスの便移植実験",
      "lines": [
        { "speaker": "ずんだもん", "text": "次にもう一つ衝撃的な実験を紹介するのだ。" },
        { "speaker": "めたん", "text": "まだあるんですの？" },
        { "speaker": "ずんだもん", "text": "うつ病患者の腸内細菌を、健康なマウスに移植した実験があるのだ。" },
        { "speaker": "めたん", "text": "腸内細菌をマウスに移すんですの？" },
        { "speaker": "ずんだもん", "text": "そう。「便移植」って呼ばれる方法なのだ。" },
        { "speaker": "ずんだもん", "text": "するとそのマウスが、うつ病的な行動を示したのだ。" },
        { "speaker": "ずんだもん", "text": "具体的には、泳ぐのを諦めたり、甘い水に興味を示さなくなったのだ。" },
        { "speaker": "めたん", "text": "腸内細菌だけで行動がそこまで変わるなんて……。" },
        { "speaker": "ずんだもん", "text": "逆に、健康な人の腸内細菌を移植すると改善する場合もあったのだ。" }
      ]
    },
    {
      "id": 22,
      "title": "動物実験の限界を正しく理解する",
      "lines": [
        { "speaker": "めたん", "text": "でも、それはマウスの話ですわよね？" },
        { "speaker": "ずんだもん", "text": "その通りなのだ。そしてここが一番大切な点なのだ。" },
        { "speaker": "ずんだもん", "text": "マウスで起きたことが、人間でも同じように起きるとは限らないのだ。" },
        { "speaker": "ずんだもん", "text": "腸脳軸の研究の多くは、まだ動物実験の段階なのだ。" },
        { "speaker": "めたん", "text": "人間で検証するのはこれからってことですわね。" },
        { "speaker": "ずんだもん", "text": "そう。だから次は、この分野の限界と最前線を見ていくのだ。" }
      ]
    },
    {
      "id": 23,
      "title": "科学の最前線と限界",
      "lines": [
        { "speaker": "ずんだもん", "text": "腸脳軸の研究はワクワクする発見が多いのだ。" },
        { "speaker": "ずんだもん", "text": "でも同時に、大きな課題もあるのだ。" },
        { "speaker": "めたん", "text": "どんな課題ですの？" }
      ]
    },
    {
      "id": 24,
      "title": "腸脳軸研究の3つの課題",
      "lines": [
        { "speaker": "ずんだもん", "text": "まず1つ目。さっきも少し触れたけど……" },
        { "speaker": "ずんだもん", "text": "研究の大半がマウスなどの動物実験に基づいてることなのだ。" },
        { "speaker": "ずんだもん", "text": "マウスの腸と人間の腸は、似ているようで全然違うのだ。" },
        { "speaker": "ずんだもん", "text": "食べるものも、腸の長さも、腸内細菌の種類も違うのだ。" },
        { "speaker": "めたん", "text": "マウスで効いても、人間に使えるとは限らないんですわね。" },
        { "speaker": "ずんだもん", "text": "2つ目は「相関関係と因果関係」の問題なのだ。" }
      ]
    },
    {
      "id": 25,
      "title": "相関関係 vs 因果関係",
      "lines": [
        { "speaker": "めたん", "text": "相関と因果ですの？　どう違うんですの？" },
        { "speaker": "ずんだもん", "text": "例えば「腸内環境が悪い人にうつ病が多い」というデータがあるのだ。" },
        { "speaker": "ずんだもん", "text": "でもこれだけでは、腸が原因なのかわからないのだ。" },
        { "speaker": "めたん", "text": "うつ病のせいで食事が偏って、腸が悪くなった可能性もありますわね。" },
        { "speaker": "ずんだもん", "text": "その通りなのだ。双方向に影響し合ってるから……" },
        { "speaker": "ずんだもん", "text": "「どっちが先か」を突き止めるのが非常に難しいのだ。" },
        { "speaker": "めたん", "text": "鶏と卵みたいな問題ですわね。" },
        { "speaker": "ずんだもん", "text": "まさにそうなのだ。これを解決するには……" },
        { "speaker": "ずんだもん", "text": "大規模で長期間の臨床試験が必要なのだ。" }
      ]
    },
    {
      "id": 26,
      "title": "「第二の脳」はあくまで比喩",
      "lines": [
        { "speaker": "ずんだもん", "text": "そして3つ目。これは動画の核心でもあるのだ。" },
        { "speaker": "ずんだもん", "text": "「第二の脳」という表現そのものが、やや誇張だという指摘があるのだ。" },
        { "speaker": "めたん", "text": "え、この動画のタイトルにも入ってるのに？" },
        { "speaker": "ずんだもん", "text": "腸管神経系は確かにすごい神経ネットワークなのだ。" },
        { "speaker": "ずんだもん", "text": "でも、考えたり、感じたり、意識を持ったりはしないのだ。" },
        { "speaker": "ずんだもん", "text": "あくまで消化のプロフェッショナルであって、脳そのものではないのだ。" },
        { "speaker": "めたん", "text": "「脳」という言葉が大きすぎるんですわね。" }
      ]
    },
    {
      "id": 27,
      "title": "マイケル・ガーション教授",
      "lines": [
        { "speaker": "ずんだもん", "text": "ちなみに「第二の脳」を世界的に有名にしたのは……" },
        { "speaker": "ずんだもん", "text": "コロンビア大学のマイケル・ガーション教授なのだ。" },
        { "speaker": "ずんだもん", "text": "1999年に『The Second Brain』という本を出版したのだ。" },
        { "speaker": "ずんだもん", "text": "「消化器の神経学の父」とも呼ばれている人なのだ。" },
        { "speaker": "めたん", "text": "もう25年以上前の本なんですわね。" },
        { "speaker": "ずんだもん", "text": "ガーション教授は、腸管神経の重要性を世に伝えたかったのだ。" },
        { "speaker": "ずんだもん", "text": "でもキャッチーな名前が独り歩きして、誤解も広がったのだ。" },
        { "speaker": "めたん", "text": "科学の世界でも、名前のインパクトって大事なんですわね。" }
      ]
    },
    {
      "id": 28,
      "title": "最前線の治療研究",
      "lines": [
        { "speaker": "ずんだもん", "text": "でもね、課題があっても希望がないわけじゃないのだ。" },
        { "speaker": "ずんだもん", "text": "むしろ最前線の研究は、どんどん進んでるのだ。" },
        { "speaker": "めたん", "text": "どんな研究があるんですの？" },
        { "speaker": "ずんだもん", "text": "まず「便移植」による精神疾患治療の臨床試験が進んでるのだ。" },
        { "speaker": "めたん", "text": "さっきのマウス実験を、人間でもやろうってことですの？" },
        { "speaker": "ずんだもん", "text": "そう。2024年からカルガリー大学などで本格的に始まってるのだ。" },
        { "speaker": "ずんだもん", "text": "うつ病やOCDに対する便移植の効果を調べてるのだ。" },
        { "speaker": "めたん", "text": "SF映画みたいですわね……。" }
      ]
    },
    {
      "id": 29,
      "title": "23のRCT、1400人以上でうつ症状改善",
      "lines": [
        { "speaker": "ずんだもん", "text": "もう一つ注目されてるのが「サイコバイオティクス」なのだ。" },
        { "speaker": "めたん", "text": "サイコバイオティクスって何ですの？" },
        { "speaker": "ずんだもん", "text": "精神に良い影響を与えるプロバイオティクスのことなのだ。" },
        { "speaker": "ずんだもん", "text": "普通のプロバイオティクスの中でも、特に脳に効く菌を指すのだ。" },
        { "speaker": "ずんだもん", "text": "23の臨床試験、1400人以上を対象にしたメタ分析では……" },
        { "speaker": "ずんだもん", "text": "プロバイオティクスがうつ症状を有意に改善したという結果が出てるのだ。" },
        { "speaker": "めたん", "text": "1400人以上のデータですの。それは信頼性がありますわね。" }
      ]
    },
    {
      "id": 30,
      "title": "「これを飲めば治る」ではない",
      "lines": [
        { "speaker": "ずんだもん", "text": "でもね、大事なことを言うのだ。" },
        { "speaker": "ずんだもん", "text": "まだ「この菌を飲めばうつ病が治る」という段階ではないのだ。" },
        { "speaker": "ずんだもん", "text": "最適な菌の種類も、飲む量も、期間も、まだ研究中なのだ。" },
        { "speaker": "めたん", "text": "発展途上ということですわね。" },
        { "speaker": "ずんだもん", "text": "でも確実に、少しずつ前に進んでるのだ。" },
        { "speaker": "ずんだもん", "text": "10年後には腸内細菌を使った治療が当たり前になってるかもしれないのだ。" },
        { "speaker": "めたん", "text": "それは本当に楽しみですわ。" }
      ]
    },
    {
      "id": 31,
      "title": "今日のまとめ",
      "lines": [
        { "speaker": "ずんだもん", "text": "さて、今日の内容をまとめるのだ。" },
        { "speaker": "めたん", "text": "盛りだくさんでしたわね。整理してくださいまし。" },
        { "speaker": "ずんだもん", "text": "最初に、お腹の調子が悪いと気分が落ち込むって話をしたよね。" },
        { "speaker": "ずんだもん", "text": "これは腸脳軸による本物の生理的現象だったのだ。" },
        { "speaker": "めたん", "text": "気のせいじゃなかったんですわね。" }
      ]
    },
    {
      "id": 32,
      "title": "3つのポイント振り返り",
      "lines": [
        { "speaker": "ずんだもん", "text": "今日わかったことを3つにまとめるのだ。" },
        { "speaker": "ずんだもん", "text": "1つ目。腸には数億の神経細胞があり、脳から独立して動けるのだ。" },
        { "speaker": "ずんだもん", "text": "2つ目。腸と脳は迷走神経で双方向に通信してるのだ。" },
        { "speaker": "ずんだもん", "text": "しかも情報の80〜90%は腸から脳の方向なのだ。" },
        { "speaker": "めたん", "text": "腸ってすごくおしゃべりなんですわね。" }
      ]
    },
    {
      "id": 33,
      "title": "腸と脳の「対話」を大切にする",
      "lines": [
        { "speaker": "ずんだもん", "text": "3つ目。腸内細菌がメンタルや病気に影響する証拠は増えてるのだ。" },
        { "speaker": "ずんだもん", "text": "パーキンソン病が腸から始まるかもしれないという研究も出てきたのだ。" },
        { "speaker": "めたん", "text": "脳の病気が腸から始まるかもしれないなんて、本当に驚きでしたわ。" },
        { "speaker": "ずんだもん", "text": "でもね、大事なことを最後に言うのだ。" },
        { "speaker": "ずんだもん", "text": "「腸が脳を支配する」は、科学的には言い過ぎなのだ。" },
        { "speaker": "めたん", "text": "え？　この動画のテーマなのに？" }
      ]
    },
    {
      "id": 34,
      "title": "正しい知識で腸と向き合う",
      "lines": [
        { "speaker": "ずんだもん", "text": "正しくは「腸と脳は対話している」なのだ。" },
        { "speaker": "ずんだもん", "text": "支配でも従属でもなく、お互いに情報を交換し合ってるのだ。" },
        { "speaker": "めたん", "text": "支配じゃなくて、対話。素敵な言い方ですわね。" },
        { "speaker": "ずんだもん", "text": "腸活ブームでいろんな情報が溢れてるのだ。" },
        { "speaker": "ずんだもん", "text": "でも「これを飲めば全部解決」なんて魔法の食品はないのだ。" },
        { "speaker": "ずんだもん", "text": "大切なのは、正しい知識で自分の体と向き合うことなのだ。" },
        { "speaker": "ずんだもん", "text": "バランスのいい食事、食物繊維、適度な運動。" },
        { "speaker": "ずんだもん", "text": "地味だけど、これが腸と脳の対話を良くする一番の近道なのだ。" },
        { "speaker": "めたん", "text": "ファクトに基づいて、自分の体を知るのが一番ですわね。" },
        { "speaker": "ずんだもん", "text": "腸と脳の対話を、みんなも大切にしてほしいのだ。" },
        { "speaker": "めたん", "text": "今日もためになるお話、ありがとうございましたわ！" },
        { "speaker": "ずんだもん", "text": "こちらこそなのだ！" }
      ]
    }
  ]
}
