{
  "voicevox_url": "http://localhost:50021",
  "speakers": {
    "zundamon": 3,
    "metan": 2
  },
  "speed_scale": 1,
  "inter_line_silence": 0.3,
  "scene_end_padding": 0.5,
  "scenes": [
    {
      "id": 0,
      "title": "scene_0",
      "lines": [
        {
          "speaker": "metan",
          "text": "今日のテーマはサブリミナル効果ですわね。"
        },
        {
          "speaker": "zundamon",
          "text": "うん。映画館でコーラの売上が激増したって話、聞いたことあるのだ？"
        },
        {
          "speaker": "metan",
          "text": "ありますわ！無意識にメッセージを受け取って行動が変わるっていう、あの有名な話ですわよね。"
        },
        {
          "speaker": "zundamon",
          "text": "そうそう。でもね、今日はその話の「本当の結末」を話すのだ。"
        }
      ]
    },
    {
      "id": 1,
      "title": "scene_1",
      "lines": [
        {
          "speaker": "zundamon",
          "text": "1957年、アメリカの広告マン、ジェームズ・ヴィカリーがある発表をしたのだ。"
        },
        {
          "speaker": "zundamon",
          "text": "映画の上映中に「コーラを飲め」「ポップコーンを食べろ」というメッセージを挿入したのだ。"
        },
        {
          "speaker": "zundamon",
          "text": "その時間はわずか3000分の1秒。人間の意識では認識できないレベルなのだ。"
        },
        {
          "speaker": "metan",
          "text": "3000分の1秒！？そんなの絶対気づかないですわ。"
        },
        {
          "speaker": "zundamon",
          "text": "その結果、コーラの売上が18.1%、ポップコーンが57.5%も増えたと主張したのだ。"
        },
        {
          "speaker": "metan",
          "text": "すごい数字ですわね！それは広告業界が飛びつきそうですわ。"
        }
      ]
    },
    {
      "id": 2,
      "title": "scene_2",
      "lines": [
        {
          "speaker": "zundamon",
          "text": "でもね、この話には衝撃的な結末があるのだ。"
        },
        {
          "speaker": "zundamon",
          "text": "これ、全部嘘だったのだ。"
        },
        {
          "speaker": "metan",
          "text": "えっ！？嘘って、どういうことですの！？"
        },
        {
          "speaker": "zundamon",
          "text": "ヴィカリー本人が1962年に告白したのだ。「あれはギミックだった」とね。"
        },
        {
          "speaker": "metan",
          "text": "ギミック？つまりでっちあげのトリックだったってことですの？"
        }
      ]
    },
    {
      "id": 3,
      "title": "scene_3",
      "lines": [
        {
          "speaker": "zundamon",
          "text": "そうなのだ。彼は当時、自分のマーケティング会社の経営に困っていたのだ。"
        },
        {
          "speaker": "zundamon",
          "text": "顧客を集めるために、でっちあげの実験結果を発表したと認めたのだ。"
        },
        {
          "speaker": "zundamon",
          "text": "データは「小さすぎて意味がない」とも告白しているのだ。"
        },
        {
          "speaker": "metan",
          "text": "自分で認めてたんですのね……"
        },
        {
          "speaker": "zundamon",
          "text": "しかもね、後から映画館の支配人にインタビューしたら……"
        },
        {
          "speaker": "zundamon",
          "text": "ヴィカリーの存在も実験装置の設置も、全く知らなかったのだ。"
        },
        {
          "speaker": "metan",
          "text": "じゃあ実験そのものが行われてなかった可能性があるってことですの！？"
        },
        {
          "speaker": "zundamon",
          "text": "そうなのだ。サブリミナル効果は、嘘から始まったのだ。"
        },
        {
          "speaker": "zundamon",
          "text": "今日はこの神話を科学の視点から徹底的に解き明かしていくのだ。"
        }
      ]
    },
    {
      "id": 4,
      "title": "scene_4",
      "lines": [
        {
          "speaker": "metan",
          "text": "でもちょっと待ってくださいまし。"
        },
        {
          "speaker": "metan",
          "text": "ヴィカリーの実験が嘘だったのはわかりましたわ。"
        },
        {
          "speaker": "metan",
          "text": "でもサブリミナルって概念自体は、科学的に何か根拠があるんじゃないですの？"
        },
        {
          "speaker": "zundamon",
          "text": "実はそう単純じゃないのだ。ここを正しく整理するのがすごく大事なのだ。"
        }
      ]
    },
    {
      "id": 5,
      "title": "scene_5",
      "lines": [
        {
          "speaker": "zundamon",
          "text": "まず「閾下知覚」っていう言葉を覚えてほしいのだ。"
        },
        {
          "speaker": "metan",
          "text": "いきかちかく？なんだか難しそうな言葉ですわね。"
        },
        {
          "speaker": "zundamon",
          "text": "「閾」は「しきい値」、つまり境界線のことなのだ。"
        },
        {
          "speaker": "zundamon",
          "text": "意識できるかどうかのボーダーラインだね。"
        },
        {
          "speaker": "zundamon",
          "text": "その閾値より下の刺激を脳が処理する現象が「閾下知覚」なのだ。"
        },
        {
          "speaker": "metan",
          "text": "つまり、意識できないレベルの刺激を脳が受け取ってるってことですの？"
        },
        {
          "speaker": "zundamon",
          "text": "その通りなのだ。"
        }
      ]
    },
    {
      "id": 6,
      "title": "scene_6",
      "lines": [
        {
          "speaker": "zundamon",
          "text": "そしてこの研究は意外と歴史が古いのだ。"
        },
        {
          "speaker": "zundamon",
          "text": "1863年にロシアのススロワ、1884年にアメリカのピアースとジャストロウが実験をしているのだ。"
        },
        {
          "speaker": "zundamon",
          "text": "意識できないレベルの刺激でも、人はそれを弁別できるということを示したのだ。"
        },
        {
          "speaker": "metan",
          "text": "ヴィカリーの1957年よりも100年近く前ですわね！"
        },
        {
          "speaker": "zundamon",
          "text": "1897年にはイエール大学のスクリプチャーが本にまとめているのだ。"
        },
        {
          "speaker": "zundamon",
          "text": "つまり閾下知覚そのものは、100年以上の歴史がある正統な研究テーマなのだ。"
        }
      ]
    },
    {
      "id": 7,
      "title": "scene_7",
      "lines": [
        {
          "speaker": "zundamon",
          "text": "実際、現代の脳科学でも面白いことがわかっているのだ。"
        },
        {
          "speaker": "zundamon",
          "text": "fMRIという装置で脳の活動を見ると、閾下の刺激に対しても反応があるのだ。"
        },
        {
          "speaker": "zundamon",
          "text": "扁桃体や海馬が活性化することが確認されているのだ。"
        },
        {
          "speaker": "metan",
          "text": "じゃあ脳は、意識できない刺激もちゃんと受け取ってるんですのね。"
        },
        {
          "speaker": "zundamon",
          "text": "そうなのだ。脳は確かに反応しているのだ。"
        }
      ]
    },
    {
      "id": 8,
      "title": "scene_8",
      "lines": [
        {
          "speaker": "zundamon",
          "text": "でもね、ここが今日の最重要ポイントなのだ。"
        },
        {
          "speaker": "zundamon",
          "text": "「脳が刺激を知覚する」ことと「その人の行動が変わる」ことは全くの別問題なのだ。"
        },
        {
          "speaker": "metan",
          "text": "あ、なるほど。感じ取ることと、それで何かを買っちゃうとかは全然違いますわよね。"
        },
        {
          "speaker": "zundamon",
          "text": "まさにそうなのだ。サブリミナル効果の問題は、ここに集約されるのだ。"
        },
        {
          "speaker": "zundamon",
          "text": "じゃあ実際に、行動を変える効果はあったのか？追試の結果を見ていくのだ。"
        }
      ]
    },
    {
      "id": 9,
      "title": "scene_9",
      "lines": [
        {
          "speaker": "metan",
          "text": "ヴィカリーの実験が嘘だったのはわかりましたわ。"
        },
        {
          "speaker": "metan",
          "text": "でも、他の研究者がちゃんと実験したらどうなったんですの？"
        },
        {
          "speaker": "zundamon",
          "text": "いい質問なのだ。答えを先に言うと……ほぼ全滅だったのだ。"
        },
        {
          "speaker": "metan",
          "text": "全滅！？"
        }
      ]
    },
    {
      "id": 10,
      "title": "scene_10",
      "lines": [
        {
          "speaker": "zundamon",
          "text": "まず1958年、ヴィカリーの発表からわずか1年後の話なのだ。"
        },
        {
          "speaker": "zundamon",
          "text": "カナダ放送協会、CBCが大規模な追試をしたのだ。"
        },
        {
          "speaker": "zundamon",
          "text": "日曜夜の人気番組「クローズアップ」の放送中にね。"
        },
        {
          "speaker": "zundamon",
          "text": "「今すぐ電話して」というメッセージを352回もサブリミナル挿入したのだ。"
        },
        {
          "speaker": "metan",
          "text": "352回！それだけやれば絶対に電話が殺到しそうですわね。"
        },
        {
          "speaker": "zundamon",
          "text": "ところが、電話は1本もかかってこなかったのだ。"
        },
        {
          "speaker": "metan",
          "text": "……1本も！？"
        }
      ]
    },
    {
      "id": 11,
      "title": "scene_11",
      "lines": [
        {
          "speaker": "zundamon",
          "text": "しかもね、約500人の視聴者にメッセージの中身を推測してもらったのだ。"
        },
        {
          "speaker": "zundamon",
          "text": "正解者はゼロだったのだ。"
        },
        {
          "speaker": "metan",
          "text": "352回も流して、当てた人がゼロですの……"
        },
        {
          "speaker": "zundamon",
          "text": "でもね、ここからが面白いのだ。"
        },
        {
          "speaker": "zundamon",
          "text": "ヴィカリーの実験を知っていた視聴者の半数近くが、こう言ったのだ。"
        },
        {
          "speaker": "zundamon",
          "text": "「なんだか空腹や喉の渇きを感じた」とね。"
        },
        {
          "speaker": "metan",
          "text": "え？でもメッセージは「電話して」でしょう？食欲と関係ないですわ。"
        }
      ]
    },
    {
      "id": 12,
      "title": "scene_12",
      "lines": [
        {
          "speaker": "zundamon",
          "text": "そうなのだ。つまりサブリミナルメッセージの効果ではなくて……"
        },
        {
          "speaker": "zundamon",
          "text": "「サブリミナルは食欲に効くらしい」という先入観が体験を作っていたのだ。"
        },
        {
          "speaker": "zundamon",
          "text": "もうこの段階で、効果の正体がうっすら見えてきたのだ。"
        },
        {
          "speaker": "metan",
          "text": "言われてみれば、思い込みの力って怖いですわね……"
        }
      ]
    },
    {
      "id": 13,
      "title": "scene_13",
      "lines": [
        {
          "speaker": "zundamon",
          "text": "じゃあ次に「唯一の成功例」と言われた実験を紹介するのだ。"
        },
        {
          "speaker": "zundamon",
          "text": "2006年にオランダのカレマンスたちが行った実験なのだ。"
        },
        {
          "speaker": "zundamon",
          "text": "コンピューター画面に「リプトンアイス」という文字を23ミリ秒だけ表示したのだ。"
        },
        {
          "speaker": "zundamon",
          "text": "23ミリ秒は、まばたきの10分の1以下の時間なのだ。"
        },
        {
          "speaker": "metan",
          "text": "そんな短い時間で、効果はあったんですの？"
        }
      ]
    },
    {
      "id": 14,
      "title": "scene_14",
      "lines": [
        {
          "speaker": "zundamon",
          "text": "結果は部分的に「あった」のだ。ただし、大きな但し書きつきでね。"
        },
        {
          "speaker": "zundamon",
          "text": "リプトンアイスを選ぶ割合が増えたのは、喉が渇いている被験者だけだったのだ。"
        },
        {
          "speaker": "metan",
          "text": "喉が渇いてない人には効かなかったんですの？"
        },
        {
          "speaker": "zundamon",
          "text": "そうなのだ。つまりこの実験が示したのは……"
        },
        {
          "speaker": "zundamon",
          "text": "新しい欲求を作り出す力ではなく、もともとある欲求をちょっとだけ増幅する程度の効果なのだ。"
        },
        {
          "speaker": "metan",
          "text": "ヴィカリーが主張したような、強力なマインドコントロールとは程遠いですわね。"
        }
      ]
    },
    {
      "id": 15,
      "title": "scene_15",
      "lines": [
        {
          "speaker": "zundamon",
          "text": "しかもね、この実験すら後から別チームが追試に失敗しているのだ。"
        },
        {
          "speaker": "zundamon",
          "text": "同じ条件で実験しても、効果が再現されなかったのだ。"
        },
        {
          "speaker": "metan",
          "text": "唯一の成功例も怪しくなってきましたわね……"
        }
      ]
    },
    {
      "id": 16,
      "title": "scene_16",
      "lines": [
        {
          "speaker": "zundamon",
          "text": "そして決定的なのが、1996年のトラッピーによるメタ分析なのだ。"
        },
        {
          "speaker": "metan",
          "text": "メタ分析って、複数の研究をまとめて分析するやつですわよね？"
        },
        {
          "speaker": "zundamon",
          "text": "そうなのだ。科学の世界で最も信頼性が高い分析手法の一つなのだ。"
        },
        {
          "speaker": "zundamon",
          "text": "サブリミナル広告に関する複数の研究をまとめて分析した結果……"
        },
        {
          "speaker": "zundamon",
          "text": "効果は「良くてもほぼゼロ」と結論づけられたのだ。"
        },
        {
          "speaker": "metan",
          "text": "メタ分析でもほぼゼロ……もう完全に否定されてるようなものですわね。"
        },
        {
          "speaker": "zundamon",
          "text": "でもね、ここからが本当に面白い話なのだ。"
        },
        {
          "speaker": "zundamon",
          "text": "効果がないのに、なぜ人は「効いた」と感じるのか。その秘密に迫るのだ。"
        }
      ]
    },
    {
      "id": 17,
      "title": "scene_17",
      "lines": [
        {
          "speaker": "zundamon",
          "text": "1991年に、サブリミナル効果の正体を暴いた非常に有名な実験があるのだ。"
        },
        {
          "speaker": "metan",
          "text": "正体を暴いた？なんだかミステリー小説みたいですわね。"
        },
        {
          "speaker": "zundamon",
          "text": "うん、実際に謎解きみたいで面白いのだ。"
        }
      ]
    },
    {
      "id": 18,
      "title": "scene_18",
      "lines": [
        {
          "speaker": "zundamon",
          "text": "ワシントン大学のグリーンウォルドたちが行った実験なのだ。"
        },
        {
          "speaker": "zundamon",
          "text": "228人の被験者に、サブリミナル自己啓発テープを1ヶ月間毎日聞いてもらったのだ。"
        },
        {
          "speaker": "metan",
          "text": "自己啓発テープ？聞くだけで自信がつくとか記憶力が上がるとかいうやつですの？"
        },
        {
          "speaker": "zundamon",
          "text": "そう。当時アメリカでは年間数百万本も売れていた大人気商品だったのだ。"
        },
        {
          "speaker": "zundamon",
          "text": "日本でもビクターが30種類のサブリミナルCDを発売して、累計100万枚超えだったのだ。"
        },
        {
          "speaker": "metan",
          "text": "100万枚も！？すごい市場ですわね。"
        }
      ]
    },
    {
      "id": 19,
      "title": "scene_19",
      "lines": [
        {
          "speaker": "zundamon",
          "text": "でもこの実験の天才的なところは「二重盲検」のデザインなのだ。"
        },
        {
          "speaker": "zundamon",
          "text": "テープの中身とラベルを、わざと入れ替えたのだ。"
        },
        {
          "speaker": "metan",
          "text": "入れ替えた？"
        },
        {
          "speaker": "zundamon",
          "text": "「記憶力向上」のラベルが貼ってあるテープに、実際には自尊心向上の内容を入れたのだ。"
        },
        {
          "speaker": "zundamon",
          "text": "逆に「自尊心向上」ラベルのテープには記憶力向上の内容を入れたのだ。"
        },
        {
          "speaker": "metan",
          "text": "なるほど！それなら本当にサブリミナルの中身が効いているのか……"
        },
        {
          "speaker": "metan",
          "text": "それともラベルの影響なのかがはっきりわかりますわね。"
        },
        {
          "speaker": "zundamon",
          "text": "被験者も研究者も、どのテープに何が入っているか知らない完全な二重盲検だったのだ。"
        }
      ]
    },
    {
      "id": 20,
      "title": "scene_20",
      "lines": [
        {
          "speaker": "zundamon",
          "text": "1ヶ月後の結果は衝撃的だったのだ。"
        },
        {
          "speaker": "zundamon",
          "text": "まず客観的な記憶テストや自尊心の心理測定では、どのグループも差はゼロだったのだ。"
        },
        {
          "speaker": "metan",
          "text": "やっぱりサブリミナルテープの中身は効かなかったんですのね。"
        },
        {
          "speaker": "zundamon",
          "text": "でもね、もっと衝撃的だったのは被験者の自己申告なのだ。"
        },
        {
          "speaker": "zundamon",
          "text": "なんと約50%が「ラベルに書いてある通りの改善を実感した」と答えたのだ。"
        }
      ]
    },
    {
      "id": 21,
      "title": "scene_21",
      "lines": [
        {
          "speaker": "metan",
          "text": "え？中身は入れ替えてあるのに、ラベル通りの効果を感じたんですの？"
        },
        {
          "speaker": "zundamon",
          "text": "そうなのだ。「記憶力向上」テープを聞いた人は記憶力が上がったと感じ……"
        },
        {
          "speaker": "zundamon",
          "text": "「自尊心向上」テープを聞いた人は自尊心が高まったと感じたのだ。"
        },
        {
          "speaker": "zundamon",
          "text": "たとえ中身が全く逆のテープだったとしてもね。"
        },
        {
          "speaker": "metan",
          "text": "つまりサブリミナルの中身は一切関係なくて……"
        },
        {
          "speaker": "zundamon",
          "text": "「このテープは記憶力を上げるものだ」という期待そのものが効果を作っていたのだ。"
        },
        {
          "speaker": "zundamon",
          "text": "研究者たちはこれを「錯覚的プラセボ効果」と名付けたのだ。"
        }
      ]
    },
    {
      "id": 22,
      "title": "scene_22",
      "lines": [
        {
          "speaker": "zundamon",
          "text": "翌年の1992年には同じチームのプラトカニスが論文を発表したのだ。"
        },
        {
          "speaker": "zundamon",
          "text": "タイトルは「サブリミナル説得のカーゴカルト・サイエンス」なのだ。"
        },
        {
          "speaker": "metan",
          "text": "カーゴカルト・サイエンス？聞き慣れない言葉ですわね。"
        },
        {
          "speaker": "zundamon",
          "text": "「見た目は科学っぽいけど、中身は空っぽ」という意味なのだ。"
        },
        {
          "speaker": "zundamon",
          "text": "ノーベル物理学賞のファインマンが作った言葉で、疑似科学の代表的な呼び方なのだ。"
        },
        {
          "speaker": "zundamon",
          "text": "プラトカニスは「厳密な実験ではサブリミナル説得の効果はゼロだ」と結論したのだ。"
        }
      ]
    },
    {
      "id": 23,
      "title": "scene_23",
      "lines": [
        {
          "speaker": "zundamon",
          "text": "ここで大事な心理学用語を紹介するのだ。「確証バイアス」なのだ。"
        },
        {
          "speaker": "metan",
          "text": "確証バイアス？"
        },
        {
          "speaker": "zundamon",
          "text": "人は自分が信じていることを裏付ける情報ばかり集めてしまう傾向があるのだ。"
        },
        {
          "speaker": "zundamon",
          "text": "「サブリミナルは効く」と信じている人は、日常のちょっとした変化を見つけて……"
        },
        {
          "speaker": "zundamon",
          "text": "「やっぱり効いた！」と解釈してしまうのだ。"
        },
        {
          "speaker": "metan",
          "text": "逆に効かなかったことは気にしないってことですわよね。"
        },
        {
          "speaker": "zundamon",
          "text": "その通りなのだ。プラセボ効果と確証バイアスが合体すると……"
        },
        {
          "speaker": "zundamon",
          "text": "実際には何の効果もないものが「効いている」ように見えてしまうのだ。"
        },
        {
          "speaker": "metan",
          "text": "サブリミナルが効くんじゃなくて、信じたから効いた気がしただけ……"
        },
        {
          "speaker": "zundamon",
          "text": "そうなのだ。でもね、じゃあなぜ各国がわざわざ法律で禁止しているのか。"
        },
        {
          "speaker": "zundamon",
          "text": "ここにもう一つの大きな誤解があるのだ。"
        }
      ]
    },
    {
      "id": 24,
      "title": "scene_24",
      "lines": [
        {
          "speaker": "metan",
          "text": "そうですわ、ずっと気になっていたんですの。"
        },
        {
          "speaker": "metan",
          "text": "効かないなら、なぜ多くの国で禁止されてるんですの？"
        },
        {
          "speaker": "metan",
          "text": "禁止されてるってことは、やっぱり効くんじゃ……"
        },
        {
          "speaker": "zundamon",
          "text": "それが最もよくある誤解なのだ。順を追って説明するね。"
        }
      ]
    },
    {
      "id": 25,
      "title": "scene_25",
      "lines": [
        {
          "speaker": "zundamon",
          "text": "まず規制の歴史を見てみるのだ。"
        },
        {
          "speaker": "zundamon",
          "text": "最初に動いたのはイギリスで、1958年にサブリミナル広告を禁止したのだ。"
        },
        {
          "speaker": "zundamon",
          "text": "アメリカでは1974年にFCCが「公共の利益に反する」と宣言したのだ。"
        },
        {
          "speaker": "zundamon",
          "text": "オーストラリアやカナダ、EUでも同様に禁止されているのだ。"
        },
        {
          "speaker": "metan",
          "text": "日本はどうですの？"
        },
        {
          "speaker": "zundamon",
          "text": "NHKが1995年に、日本民間放送連盟が1999年に禁止を明文化したのだ。"
        }
      ]
    },
    {
      "id": 26,
      "title": "scene_26",
      "lines": [
        {
          "speaker": "zundamon",
          "text": "でもね、禁止の理由をよく読むと面白いことがわかるのだ。"
        },
        {
          "speaker": "zundamon",
          "text": "どの国も「効果があるから禁止」とは言っていないのだ。"
        },
        {
          "speaker": "zundamon",
          "text": "理由は「消費者を欺こうとする意図が問題」なのだ。"
        },
        {
          "speaker": "metan",
          "text": "効くかどうかじゃなくて、やろうとしてること自体がダメってことですの？"
        },
        {
          "speaker": "zundamon",
          "text": "そうなのだ。これは「予防原則」と呼ばれる考え方なのだ。"
        },
        {
          "speaker": "zundamon",
          "text": "効果が科学的に証明されていなくても、欺瞞的な手法は禁止するという原則なのだ。"
        },
        {
          "speaker": "metan",
          "text": "なるほど。禁止されている＝効果がある、という思い込みは間違いだったんですわね。"
        }
      ]
    },
    {
      "id": 27,
      "title": "scene_27",
      "lines": [
        {
          "speaker": "zundamon",
          "text": "しかもね、ヴィカリーの嘘が広まった背景には、時代の空気があるのだ。"
        },
        {
          "speaker": "zundamon",
          "text": "1957年は冷戦の真っ最中だったのだ。"
        },
        {
          "speaker": "zundamon",
          "text": "アメリカでは「ソ連がマインドコントロール技術を開発しているかも」という恐怖があったのだ。"
        },
        {
          "speaker": "zundamon",
          "text": "そしてなんと、CIAが1958年に報告書を作っているのだ。"
        },
        {
          "speaker": "zundamon",
          "text": "タイトルは「サブリミナル知覚の作戦的可能性」なのだ。"
        },
        {
          "speaker": "metan",
          "text": "CIAまで！？たった一人の詐欺師の嘘が、ここまで影響力を持ったんですのね……"
        },
        {
          "speaker": "zundamon",
          "text": "恐怖は人の判断力を狂わせるのだ。科学的検証より前に対策が進んでしまったのだ。"
        }
      ]
    },
    {
      "id": 28,
      "title": "scene_28",
      "lines": [
        {
          "speaker": "zundamon",
          "text": "日本でも大きな出来事があったのだ。"
        },
        {
          "speaker": "zundamon",
          "text": "1995年はオウム真理教の事件で日本中が騒然としていた時期なのだ。"
        },
        {
          "speaker": "zundamon",
          "text": "その年、アニメ「シティーハンター3」の再放送で驚くべきことが判明したのだ。"
        },
        {
          "speaker": "zundamon",
          "text": "麻原彰晃の顔が1コマだけ挿入されていたのだ。"
        },
        {
          "speaker": "metan",
          "text": "えっ、それは怖いですわ……"
        },
        {
          "speaker": "zundamon",
          "text": "TBSの報道番組でも同様の挿入が見つかって大問題になったのだ。"
        },
        {
          "speaker": "zundamon",
          "text": "この事件がきっかけで、日本でもサブリミナル手法への警戒感が一気に高まったのだ。"
        }
      ]
    },
    {
      "id": 29,
      "title": "scene_29",
      "lines": [
        {
          "speaker": "zundamon",
          "text": "ちなみに、1997年のポケモンショックをサブリミナルと混同する人が多いのだ。"
        },
        {
          "speaker": "metan",
          "text": "あの光の点滅で視聴者が体調不良になった事件ですわよね？"
        },
        {
          "speaker": "zundamon",
          "text": "そうなのだ。でもあれは光過敏性発作が原因なのだ。サブリミナル効果とは全く別物なのだ。"
        },
        {
          "speaker": "zundamon",
          "text": "赤と青の激しい点滅が、てんかん発作を引き起こしたものなのだ。"
        },
        {
          "speaker": "zundamon",
          "text": "無意識への働きかけではなく、直接的な光刺激による生理的反応なのだ。"
        },
        {
          "speaker": "metan",
          "text": "「サブリミナル」という言葉が一人歩きして、関係ないものまで結びつけられてるんですわね。"
        },
        {
          "speaker": "zundamon",
          "text": "そうなのだ。そしてそれ自体が、人が「サブリミナル」という概念に過剰な力を感じている証拠なのだ。"
        }
      ]
    },
    {
      "id": 30,
      "title": "scene_30",
      "lines": [
        {
          "speaker": "zundamon",
          "text": "さて、今日の話をまとめるのだ。ポイントは3つなのだ。"
        },
        {
          "speaker": "zundamon",
          "text": "1つ目。サブリミナル効果の「発見」は、ヴィカリーの完全な捏造だったのだ。"
        },
        {
          "speaker": "zundamon",
          "text": "実験そのものが行われていなかった可能性すらあるのだ。"
        },
        {
          "speaker": "metan",
          "text": "科学史上最大級の詐欺でしたわね。"
        },
        {
          "speaker": "zundamon",
          "text": "2つ目。その後の60年以上にわたる科学的な追試やメタ分析でも……"
        },
        {
          "speaker": "zundamon",
          "text": "サブリミナルメッセージによる行動変容の効果は、ほぼゼロだったのだ。"
        },
        {
          "speaker": "metan",
          "text": "閾下知覚は存在するけど、それで人を操れるわけじゃないんですわよね。"
        }
      ]
    },
    {
      "id": 31,
      "title": "scene_31",
      "lines": [
        {
          "speaker": "zundamon",
          "text": "そして3つ目。人が「効いた」と感じる正体は……"
        },
        {
          "speaker": "zundamon",
          "text": "プラセボ効果と確証バイアスだったのだ。信じたから効いた気がしたのだ。"
        },
        {
          "speaker": "metan",
          "text": "つまり冒頭の問いに戻ると。"
        },
        {
          "speaker": "metan",
          "text": "「サブリミナル効果で潜在意識を操れる」というのは、科学的に見て幻想だったってことですわね。"
        },
        {
          "speaker": "zundamon",
          "text": "そうなのだ。閾下知覚という現象自体は本物だけど……"
        },
        {
          "speaker": "zundamon",
          "text": "それで人の行動をコントロールできるという話は、科学的には支持されていないのだ。"
        }
      ]
    },
    {
      "id": 32,
      "title": "scene_32",
      "lines": [
        {
          "speaker": "metan",
          "text": "でもずんだもん、多くの人が今でも信じているのは事実ですわよね。"
        },
        {
          "speaker": "metan",
          "text": "なんだか皮肉な話ですわ。"
        },
        {
          "speaker": "zundamon",
          "text": "本当にそうなのだ。実は最強のサブリミナルメッセージは……"
        },
        {
          "speaker": "zundamon",
          "text": "私たち自身の「思い込み」なのかもしれないのだ。"
        },
        {
          "speaker": "metan",
          "text": "「信じれば効く」というのは、逆に言えば人の心の力がそれだけ強いってことですわよね。"
        },
        {
          "speaker": "zundamon",
          "text": "そうなのだ。だからこそ「何を信じるか」は、自分でちゃんと選びたいのだ。"
        }
      ]
    },
    {
      "id": 33,
      "title": "scene_33",
      "lines": [
        {
          "speaker": "zundamon",
          "text": "怪しい商品やサービスに「サブリミナル効果」と書いてあったら……"
        },
        {
          "speaker": "zundamon",
          "text": "今日の話を思い出してほしいのだ。"
        },
        {
          "speaker": "metan",
          "text": "科学的根拠を確認してから判断する。それが一番の防衛策ですわね。"
        },
        {
          "speaker": "zundamon",
          "text": "その通りなのだ！"
        },
        {
          "speaker": "zundamon",
          "text": "それじゃあ今日はここまでなのだ。また次の動画で会おうね！"
        },
        {
          "speaker": "metan",
          "text": "ありがとうございましたですわ！"
        }
      ]
    }
  ]
}